{
  "status": "We can win New York, but we\u2019ll need a strong grassroots effort. Let\u2019s reach 2 million calls and #TakeNYbyPhone: https://t.co/lF2MNqEXTd", 
  "milestones": {
    "percentage": 39, 
    "eta": "1492585509", 
    "hit": [
      0
    ], 
    "next": 5000000
  }, 
  "screen_name": "@BernieSanders", 
  "banner_url": "https://pbs.twimg.com/profile_banners/216776631/1451363799", 
  "url": "https://t.co/W6f7Iy1Nho", 
  "average_follower_flow": 57.166666666666664, 
  "follower_count": 1974539, 
  "nickname": "Bernie Sanders", 
  "description": "Join our campaign for president at https://t.co/nuBuflGIwb. Tweets by staff."
}